src/kodit/_version.py
mseep_kodit-0.4.4.dev2.dist-info/METADATA
mseep_kodit-0.4.4.dev2.dist-info/WHEEL
mseep_kodit-0.4.4.dev2.dist-info/entry_points.txt
mseep_kodit-0.4.4.dev2.dist-info/licenses/LICENSE
mseep_kodit-0.4.4.dev2.dist-info/RECORD
